Metadata-Version: 1.0
Name: dada-file
Version: 0.0.9
Summary: The core DadaFile object and url generation
Home-page: http://globally.ltd
Author: gltd
Author-email: hey@gltd.email
License: UNKNOWN
Platform: UNKNOWN
